{
  "gitSyncId": "691d8449549b186264d7895e_7c4b7a85-7db3-4862-be27-eec7d3754c2e",
  "id": "Page1_Template.extractKeyword",
  "pluginId": "js-plugin",
  "pluginType": "JS",
  "unpublishedAction": {
    "actionConfiguration": {
      "encodeParamsToggle": true,
      "jsArguments": [],
      "paginationType": "NONE",
      "timeoutInMillisecond": 10000
    },
    "collectionId": "Page1_Template",
    "confirmBeforeExecute": false,
    "datasource": {
      "isAutoGenerated": false,
      "name": "UNUSED_DATASOURCE",
      "pluginId": "js-plugin"
    },
    "dynamicBindingPathList": [
      {
        "key": "body"
      }
    ],
    "fullyQualifiedName": "Template.extractKeyword",
    "name": "extractKeyword",
    "pageId": "Page1",
    "runBehaviour": "MANUAL",
    "userSetOnLoad": false
  }
}