{
  "gitSyncId": "691d8449549b186264d7895e_0d3849fe-b5f4-4fbd-acf9-37d14d2dc88f",
  "id": "Page1_campaigns_cancel_schedule",
  "pluginId": "restapi-plugin",
  "pluginType": "API",
  "unpublishedAction": {
    "actionConfiguration": {
      "autoGeneratedHeaders": [
        {
          "key": "content-type",
          "value": "application/json"
        }
      ],
      "body": "",
      "bodyFormData": [],
      "encodeParamsToggle": true,
      "formData": {
        "apiContentType": "application/json"
      },
      "headers": [
        {
          "key": "X-Operator-Email",
          "value": "{{appsmith.user.email}}"
        }
      ],
      "httpMethod": "POST",
      "httpVersion": "HTTP11",
      "paginationType": "NONE",
      "path": "/api/campaigns/{{TableCampaigns.selectedRow.campaign_id}}/cancel-schedule",
      "pluginSpecifiedTemplates": [
        {
          "value": true
        }
      ],
      "queryParameters": [],
      "timeoutInMillisecond": 10000
    },
    "confirmBeforeExecute": false,
    "datasource": {
      "id": "Email Marketing API",
      "isAutoGenerated": false,
      "name": "Email Marketing API",
      "pluginId": "restapi-plugin"
    },
    "dynamicBindingPathList": [
      {
        "key": "path"
      },
      {
        "key": "headers[0].value"
      }
    ],
    "name": "campaigns_cancel_schedule",
    "pageId": "Page1",
    "runBehaviour": "MANUAL",
    "userSetOnLoad": false
  }
}